refactoring_agent/__init__.py
refactoring_agent/ai_handler.py
refactoring_agent/cli.py
refactoring_agent/config.py
refactoring_agent/github_handler.py
refactoring_agent/llm_client.py
refactoring_agent/llm_provider.py
refactoring_agent/report_html.py
refactoring_agent/report_sarif.py
refactoring_agent/scanner.py
refactoring_agent/utils.py
refactoring_agent/wizard.py
refactoring_agent-0.1.0.dist-info/METADATA
refactoring_agent-0.1.0.dist-info/WHEEL
refactoring_agent-0.1.0.dist-info/entry_points.txt
refactoring_agent-0.1.0.dist-info/top_level.txt
refactoring_agent-0.1.0.dist-info/RECORD
